mach_data_tools
