Metadata-Version: 2.1
Name: mach-data-tools
Version: 0.0.1
Summary: MACH Data Tools
Home-page: UNKNOWN
Author: sfgarcia
Author-email: <sfgarcia@uc.cl>
License: UNKNOWN
Keywords: python,analytics,data
Platform: UNKNOWN
Classifier: Development Status :: 1 - Planning
Classifier: Intended Audience :: Developers
Classifier: Programming Language :: Python :: 3
Classifier: Operating System :: Unix
Classifier: Operating System :: MacOS :: MacOS X
Classifier: Operating System :: Microsoft :: Windows
License-File: LICENCE
